{"actuacion":" Radicación de Proceso","anotacion":"Actuación de  Radicación de Proceso  realizada el 29/08/2017 a las 15:05:03","cant":32,"carpetaNumero":177,"codRegla":"00                              ","conDocumentos":false,"consActuacion":1,"createdAt":"2017-08-29T05:00:00.000Z","fechaActuacion":"2017-08-29T00:00:00.000Z","fechaFinal":"2017-08-29T00:00:00.000Z","fechaInicial":"2017-08-29T00:00:00.000Z","fechaRegistro":"2017-08-29T00:00:00.000Z","isUltimaAct":false,"llaveProceso":"11001400304520170104100","procesoId":9876793,"idProceso":9876793,"idRegActuacion":"113517573"}