{
  "idRegActuacion": 2073945480,
  "llaveProceso": "11001418907420240118200",
  "consActuacion": 22,
  "fechaActuacion": "2025-07-30T05:00:00.000Z",
  "actuacion": "Constancia secretarial",
  "anotacion": "Devolución Expediente Oficina Ejecución",
  "fechaInicial": null,
  "fechaFinal": null,
  "fechaRegistro": "2025-08-11T05:00:00.000Z",
  "codRegla": "00                              ",
  "conDocumentos": false,
  "cant": 22,
  "isUltimaAct": true,
  "idProceso": 196356060,
  "createdAt": "2025-08-11T05:00:00.000Z"
}
