{
  "idRegActuacion": 1549727120,
  "llaveProceso": "11001400304320180038400",
  "consActuacion": 109,
  "fechaActuacion": "2025-02-10T05:00:00.000Z",
  "actuacion": "Recepción memorial",
  "anotacion": "Radicado No. 2214-2025, No. Reloj Radicador: 18, Entidad o Señor(a): R&SNASESORIA JURIDICA SAS - Tercer Interesado, Aportó Documento: Memorial, Con La Solucitud: Memorial, Observaciones: SOLICITUD REQUERIR ECOPETROL",
  "fechaInicial": null,
  "fechaFinal": null,
  "fechaRegistro": "2025-02-10T05:00:00.000Z",
  "codRegla": "00                              ",
  "conDocumentos": false,
  "cant": 109,
  "isUltimaAct": true,
  "idProceso": 114256610,
  "createdAt": "2025-02-10T05:00:00.000Z"
}
