{"idRegActuacion":1212562314,"llaveProceso":"11001310302520170073600","consActuacion":102,"fechaActuacion":"2025-02-10T05:00:00.000Z","actuacion":"Recepción memorial","anotacion":"Radicado No. 1392-2025, Entidad o Señor(a): CARMEN RAMIREZ - Tercer Interesado, Aportó Documento: Memorial, Con La Solucitud: Memorial, Observaciones: IMPULSO PROCESAL RENUNCIA PODER\r\nDe: R & S ASESORIA JURIDICA SAS <rscojuez@gmail.com>\r\nEnviado: lunes, 10 de febrero de 2025 8:10\r\n11001310302520170073600 JDO 2 // JG // FL 8","fechaInicial":null,"fechaFinal":null,"fechaRegistro":"2025-02-10T05:00:00.000Z","codRegla":"00                              ","conDocumentos":false,"cant":102,"isUltimaAct":true,"idProceso":28937944,"createdAt":"2025-02-10T05:00:00.000Z"}